{
  "artifact": "ACTIVE_ORDER_LOCK",
  "project": "STOCK_ZERO",
  "status": "ACTIVE",
  "phase": "FAST_REFORM_009F_REPO_ORGANIZATION_CLEANUP",
  "base_main_commit": "5148b5d",
  "order": [
    "PR #19, PR #20 and PR #21 are merged to main.",
    "Create repo organization cleanup inventory under governance/cleanup.",
    "Classify merged 009F branches and worktree-bound branches.",
    "Do not delete branches or worktrees in this manifest commit.",
    "Open PR for cleanup manifest and status lock update."
  ],
  "allowed_now": [
    "create governance/cleanup inventory artifacts",
    "update PROJECT_STATUS_INDEX.json to cleanup phase",
    "update ACTIVE_ORDER_LOCK.json to cleanup phase",
    "validate JSON artifacts",
    "review diff",
    "commit explicit files only",
    "push cleanup branch",
    "open PR"
  ],
  "forbidden_now": [
    "DB apply",
    "009G implementation",
    "SQL apply",
    "loader patch",
    "file deletion",
    "branch deletion",
    "worktree deletion",
    "data movement",
    "destructive cleanup",
    "git add ."
  ],
  "close_condition": [
    "cleanup manifest exists",
    "cleanup summary exists",
    "PROJECT_STATUS_INDEX points to cleanup phase",
    "ACTIVE_ORDER_LOCK points to cleanup phase",
    "JSON validation passes",
    "git diff --check passes",
    "PR merged to main"
  ],
  "next_allowed_phase_after_close": "OPTIONAL_BRANCH_DELETE_GATE_FOR_SAFE_009F_BRANCHES",
  "active_branch": "lab/FAST_REFORM_009F_repo_organization_cleanup"
}
